{
  "data": [
    {
      "player_id": "pl_29805153",
      "player_name": "Orkun Kökçü",
      "team_id": "tm_10361",
      "club_team_id": "tm_63118",
      "position": "M",
      "rating": 8.19,
      "started": true,
      "played": true,
      "minutes_played": 90,
      "passing": {
        "total_passes": 93,
        "accurate_passes": 90,
        "key_passes": 2,
        "assists": 0,
        "total_crosses": 2,
        "accurate_crosses": 0,
        "total_long_balls": 6,
        "accurate_long_balls": 5
      },
      "shooting": {
        "goals": 0,
        "total_shots": 2,
        "shots_on_target": 0,
        "shots_off_target": 1,
        "blocked_shots": 1,
        "big_chances_created": 0,
        "expected_goals": 0,
        "expected_assists": 0,
        "np_expected_goals": null
      },
      "duels": {
        "duel_won": 3,
        "duel_lost": 5,
        "aerial_won": 0,
        "challenge_lost": 1,
        "won_contest": 2,
        "dispossessed": 2
      },
      "defending": {
        "tackles": 1,
        "interceptions": 0,
        "clearances": 0
      },
      "goalkeeping": {
        "saves": 0
      },
      "general": {
        "touches": 107,
        "fouls": 1,
        "was_fouled": 0,
        "offsides": 0,
        "yellow_cards": 0,
        "red_cards": 0,
        "possession_lost": 12,
        "player_subbed_on": "pl_29665939",
        "player_subbed_off": null
      }
    },
    {
      "player_id": "pl_3605532",
      "player_name": "Gabriel Paulista",
      "team_id": "tm_10361",
      "club_team_id": "tm_36208",
      "position": "D",
      "rating": 7.83,
      "started": true,
      "played": true,
      "minutes_played": 90,
      "passing": {
        "total_passes": 112,
        "accurate_passes": 107,
        "key_passes": 0,
        "assists": 0,
        "total_crosses": 0,
        "accurate_crosses": 0,
        "total_long_balls": 11,
        "accurate_long_balls": 8
      },
      "shooting": {
        "goals": 0,
        "total_shots": 0,
        "shots_on_target": 0,
        "shots_off_target": 0,
        "blocked_shots": 0,
        "big_chances_created": 0,
        "expected_goals": 0,
        "expected_assists": 0,
        "np_expected_goals": null
      },
      "duels": {
        "duel_won": 3,
        "duel_lost": 3,
        "aerial_won": 1,
        "challenge_lost": 0,
        "won_contest": 1,
        "dispossessed": 0
      },
      "defending": {
        "tackles": 1,
        "interceptions": 0,
        "clearances": 2
      },
      "goalkeeping": {
        "saves": 0
      },
      "general": {
        "touches": 116,
        "fouls": 1,
        "was_fouled": 0,
        "offsides": 0,
        "yellow_cards": 0,
        "red_cards": 0,
        "possession_lost": 5,
        "player_subbed_on": null,
        "player_subbed_off": null
      }
    },
    {
      "player_id": "pl_72023099",
      "player_name": "Emirhan Topçu",
      "team_id": "tm_10361",
      "club_team_id": null,
      "position": "D",
      "rating": 7.93,
      "started": true,
      "played": true,
      "minutes_played": 90,
      "passing": {
        "total_passes": 114,
        "accurate_passes": 108,
        "key_passes": 0,
        "assists": 0,
        "total_crosses": 0,
        "accurate_crosses": 0,
        "total_long_balls": 10,
        "accurate_long_balls": 9
      },
      "shooting": {
        "goals": 0,
        "total_shots": 0,
        "shots_on_target": 0,
        "shots_off_target": 0,
        "blocked_shots": 0,
        "big_chances_created": 0,
        "expected_goals": 0,
        "expected_assists": 0,
        "np_expected_goals": null
      },
      "duels": {
        "duel_won": 6,
        "duel_lost": 2,
        "aerial_won": 1,
        "challenge_lost": 0,
        "won_contest": 0,
        "dispossessed": 1
      },
      "defending": {
        "tackles": 4,
        "interceptions": 0,
        "clearances": 4
      },
      "goalkeeping": {
        "saves": 0
      },
      "general": {
        "touches": 125,
        "fouls": 0,
        "was_fouled": 1,
        "offsides": 0,
        "yellow_cards": 0,
        "red_cards": 0,
        "possession_lost": 7,
        "player_subbed_on": null,
        "player_subbed_off": null
      }
    },
    {
      "player_id": "pl_2971362",
      "player_name": "João Mário",
      "team_id": "tm_10361",
      "club_team_id": null,
      "position": "F",
      "rating": 7.2,
      "started": true,
      "played": true,
      "minutes_played": 90,
      "passing": {
        "total_passes": 40,
        "accurate_passes": 33,
        "key_passes": 2,
        "assists": 1,
        "total_crosses": 0,
        "accurate_crosses": 0,
        "total_long_balls": 1,
        "accurate_long_balls": 1
      },
      "shooting": {
        "goals": 1,
        "total_shots": 3,
        "shots_on_target": 1,
        "shots_off_target": 0,
        "blocked_shots": 2,
        "big_chances_created": 1,
        "expected_goals": 0,
        "expected_assists": 0,
        "np_expected_goals": null
      },
      "duels": {
        "duel_won": 1,
        "duel_lost": 5,
        "aerial_won": 1,
        "challenge_lost": 2,
        "won_contest": 0,
        "dispossessed": 1
      },
      "defending": {
        "tackles": 0,
        "interceptions": 0,
        "clearances": 1
      },
      "goalkeeping": {
        "saves": 0
      },
      "general": {
        "touches": 48,
        "fouls": 2,
        "was_fouled": 0,
        "offsides": 0,
        "yellow_cards": 0,
        "red_cards": 0,
        "possession_lost": 10,
        "player_subbed_on": null,
        "player_subbed_off": null
      }
    },
    {
      "player_id": "pl_536846",
      "player_name": "Mert Günok",
      "team_id": "tm_10361",
      "club_team_id": "tm_91646",
      "position": "G",
      "rating": 6.84,
      "started": true,
      "played": true,
      "minutes_played": 90,
      "passing": {
        "total_passes": 17,
        "accurate_passes": 14,
        "key_passes": 0,
        "assists": 0,
        "total_crosses": 0,
        "accurate_crosses": 0,
        "total_long_balls": 5,
        "accurate_long_balls": 2
      },
      "shooting": {
        "goals": 0,
        "total_shots": 0,
        "shots_on_target": 0,
        "shots_off_target": 0,
        "blocked_shots": 0,
        "big_chances_created": 0,
        "expected_goals": 0,
        "expected_assists": 0,
        "np_expected_goals": null
      },
      "duels": {
        "duel_won": 0,
        "duel_lost": 0,
        "aerial_won": 0,
        "challenge_lost": 0,
        "won_contest": 0,
        "dispossessed": 0
      },
      "defending": {
        "tackles": 0,
        "interceptions": 0,
        "clearances": 0
      },
      "goalkeeping": {
        "saves": 2
      },
      "general": {
        "touches": 28,
        "fouls": 0,
        "was_fouled": 0,
        "offsides": 0,
        "yellow_cards": 0,
        "red_cards": 0,
        "possession_lost": 4,
        "player_subbed_on": null,
        "player_subbed_off": null
      }
    },
    {
      "player_id": "pl_13761573",
      "player_name": "Ernest Muçi",
      "team_id": "tm_10361",
      "club_team_id": null,
      "position": "F",
      "rating": 6.29,
      "started": true,
      "played": true,
      "minutes_played": 59,
      "passing": {
        "total_passes": 23,
        "accurate_passes": 19,
        "key_passes": 1,
        "assists": 0,
        "total_crosses": 1,
        "accurate_crosses": 1,
        "total_long_balls": 0,
        "accurate_long_balls": 0
      },
      "shooting": {
        "goals": 0,
        "total_shots": 1,
        "shots_on_target": 1,
        "shots_off_target": 0,
        "blocked_shots": 0,
        "big_chances_created": 0,
        "expected_goals": 0,
        "expected_assists": 0,
        "np_expected_goals": null
      },
      "duels": {
        "duel_won": 3,
        "duel_lost": 3,
        "aerial_won": 0,
        "challenge_lost": 1,
        "won_contest": 1,
        "dispossessed": 0
      },
      "defending": {
        "tackles": 1,
        "interceptions": 0,
        "clearances": 0
      },
      "goalkeeping": {
        "saves": 0
      },
      "general": {
        "touches": 33,
        "fouls": 0,
        "was_fouled": 1,
        "offsides": 0,
        "yellow_cards": 0,
        "red_cards": 0,
        "possession_lost": 8,
        "player_subbed_on": "pl_25132677",
        "player_subbed_off": null
      }
    },
    {
      "player_id": "pl_61148026",
      "player_name": "Tammy Abraham",
      "team_id": "tm_10361",
      "club_team_id": "tm_1002",
      "position": "F",
      "rating": 9.71,
      "started": true,
      "played": true,
      "minutes_played": 90,
      "passing": {
        "total_passes": 14,
        "accurate_passes": 12,
        "key_passes": 1,
        "assists": 0,
        "total_crosses": 0,
        "accurate_crosses": 0,
        "total_long_balls": 0,
        "accurate_long_balls": 0
      },
      "shooting": {
        "goals": 3,
        "total_shots": 3,
        "shots_on_target": 3,
        "shots_off_target": 0,
        "blocked_shots": 0,
        "big_chances_created": 0,
        "expected_goals": 0,
        "expected_assists": 0,
        "np_expected_goals": null
      },
      "duels": {
        "duel_won": 4,
        "duel_lost": 6,
        "aerial_won": 0,
        "challenge_lost": 0,
        "won_contest": 1,
        "dispossessed": 2
      },
      "defending": {
        "tackles": 2,
        "interceptions": 0,
        "clearances": 1
      },
      "goalkeeping": {
        "saves": 0
      },
      "general": {
        "touches": 26,
        "fouls": 2,
        "was_fouled": 1,
        "offsides": 0,
        "yellow_cards": 0,
        "red_cards": 0,
        "possession_lost": 5,
        "player_subbed_on": null,
        "player_subbed_off": null
      }
    },
    {
      "player_id": "pl_29263116",
      "player_name": "David Jurásek",
      "team_id": "tm_10361",
      "club_team_id": "tm_64842",
      "position": "D",
      "rating": 6.32,
      "started": true,
      "played": true,
      "minutes_played": 90,
      "passing": {
        "total_passes": 46,
        "accurate_passes": 42,
        "key_passes": 0,
        "assists": 0,
        "total_crosses": 1,
        "accurate_crosses": 0,
        "total_long_balls": 1,
        "accurate_long_balls": 1
      },
      "shooting": {
        "goals": 0,
        "total_shots": 0,
        "shots_on_target": 0,
        "shots_off_target": 0,
        "blocked_shots": 0,
        "big_chances_created": 0,
        "expected_goals": 0,
        "expected_assists": 0,
        "np_expected_goals": null
      },
      "duels": {
        "duel_won": 1,
        "duel_lost": 2,
        "aerial_won": 0,
        "challenge_lost": 0,
        "won_contest": 0,
        "dispossessed": 0
      },
      "defending": {
        "tackles": 1,
        "interceptions": 0,
        "clearances": 0
      },
      "goalkeeping": {
        "saves": 0
      },
      "general": {
        "touches": 57,
        "fouls": 3,
        "was_fouled": 0,
        "offsides": 0,
        "yellow_cards": 0,
        "red_cards": 0,
        "possession_lost": 9,
        "player_subbed_on": "pl_72536535",
        "player_subbed_off": null
      }
    },
    {
      "player_id": "pl_3868860",
      "player_name": "Rafa Silva",
      "team_id": "tm_10361",
      "club_team_id": "tm_63118",
      "position": "M",
      "rating": 6.09,
      "started": true,
      "played": true,
      "minutes_played": 90,
      "passing": {
        "total_passes": 52,
        "accurate_passes": 43,
        "key_passes": 3,
        "assists": 1,
        "total_crosses": 0,
        "accurate_crosses": 0,
        "total_long_balls": 2,
        "accurate_long_balls": 2
      },
      "shooting": {
        "goals": 0,
        "total_shots": 2,
        "shots_on_target": 0,
        "shots_off_target": 2,
        "blocked_shots": 0,
        "big_chances_created": 0,
        "expected_goals": 0,
        "expected_assists": 0,
        "np_expected_goals": null
      },
      "duels": {
        "duel_won": 2,
        "duel_lost": 2,
        "aerial_won": 0,
        "challenge_lost": 0,
        "won_contest": 1,
        "dispossessed": 0
      },
      "defending": {
        "tackles": 1,
        "interceptions": 0,
        "clearances": 0
      },
      "goalkeeping": {
        "saves": 0
      },
      "general": {
        "touches": 59,
        "fouls": 0,
        "was_fouled": 0,
        "offsides": 0,
        "yellow_cards": 0,
        "red_cards": 0,
        "possession_lost": 12,
        "player_subbed_on": null,
        "player_subbed_off": null
      }
    },
    {
      "player_id": "pl_58717116",
      "player_name": "Demir Ege Tıknaz",
      "team_id": "tm_10361",
      "club_team_id": "tm_79214",
      "position": "M",
      "rating": 7.67,
      "started": true,
      "played": true,
      "minutes_played": 76,
      "passing": {
        "total_passes": 59,
        "accurate_passes": 55,
        "key_passes": 1,
        "assists": 0,
        "total_crosses": 0,
        "accurate_crosses": 0,
        "total_long_balls": 2,
        "accurate_long_balls": 1
      },
      "shooting": {
        "goals": 0,
        "total_shots": 1,
        "shots_on_target": 1,
        "shots_off_target": 0,
        "blocked_shots": 0,
        "big_chances_created": 0,
        "expected_goals": 0,
        "expected_assists": 0,
        "np_expected_goals": null
      },
      "duels": {
        "duel_won": 7,
        "duel_lost": 3,
        "aerial_won": 0,
        "challenge_lost": 0,
        "won_contest": 1,
        "dispossessed": 1
      },
      "defending": {
        "tackles": 5,
        "interceptions": 1,
        "clearances": 2
      },
      "goalkeeping": {
        "saves": 0
      },
      "general": {
        "touches": 71,
        "fouls": 2,
        "was_fouled": 1,
        "offsides": 0,
        "yellow_cards": 1,
        "red_cards": 0,
        "possession_lost": 5,
        "player_subbed_on": "pl_29100926",
        "player_subbed_off": null
      }
    },
    {
      "player_id": "pl_7257031",
      "player_name": "Jonas Svensson",
      "team_id": "tm_10361",
      "club_team_id": "tm_29703",
      "position": "D",
      "rating": 7.1,
      "started": true,
      "played": true,
      "minutes_played": 45,
      "passing": {
        "total_passes": 25,
        "accurate_passes": 24,
        "key_passes": 0,
        "assists": 0,
        "total_crosses": 0,
        "accurate_crosses": 0,
        "total_long_balls": 0,
        "accurate_long_balls": 0
      },
      "shooting": {
        "goals": 0,
        "total_shots": 0,
        "shots_on_target": 0,
        "shots_off_target": 0,
        "blocked_shots": 0,
        "big_chances_created": 0,
        "expected_goals": 0,
        "expected_assists": 0,
        "np_expected_goals": null
      },
      "duels": {
        "duel_won": 2,
        "duel_lost": 4,
        "aerial_won": 0,
        "challenge_lost": 0,
        "won_contest": 0,
        "dispossessed": 0
      },
      "defending": {
        "tackles": 1,
        "interceptions": 0,
        "clearances": 1
      },
      "goalkeeping": {
        "saves": 0
      },
      "general": {
        "touches": 31,
        "fouls": 2,
        "was_fouled": 1,
        "offsides": 0,
        "yellow_cards": 0,
        "red_cards": 0,
        "possession_lost": 1,
        "player_subbed_on": "pl_3875532",
        "player_subbed_off": null
      }
    },
    {
      "player_id": "pl_30485343",
      "player_name": "Tom Grivosti",
      "team_id": "tm_79322",
      "club_team_id": null,
      "position": "D",
      "rating": 6.58,
      "started": true,
      "played": true,
      "minutes_played": 45,
      "passing": {
        "total_passes": 25,
        "accurate_passes": 22,
        "key_passes": 0,
        "assists": 0,
        "total_crosses": 0,
        "accurate_crosses": 0,
        "total_long_balls": 5,
        "accurate_long_balls": 4
      },
      "shooting": {
        "goals": 0,
        "total_shots": 0,
        "shots_on_target": 0,
        "shots_off_target": 0,
        "blocked_shots": 0,
        "big_chances_created": 0,
        "expected_goals": 0,
        "expected_assists": 0,
        "np_expected_goals": null
      },
      "duels": {
        "duel_won": 1,
        "duel_lost": 1,
        "aerial_won": 0,
        "challenge_lost": 1,
        "won_contest": 0,
        "dispossessed": 0
      },
      "defending": {
        "tackles": 1,
        "interceptions": 0,
        "clearances": 0
      },
      "goalkeeping": {
        "saves": 0
      },
      "general": {
        "touches": 27,
        "fouls": 0,
        "was_fouled": 0,
        "offsides": 0,
        "yellow_cards": 0,
        "red_cards": 0,
        "possession_lost": 3,
        "player_subbed_on": "pl_83279934",
        "player_subbed_off": null
      }
    },
    {
      "player_id": "pl_57338255",
      "player_name": "Jamie Lennon",
      "team_id": "tm_79322",
      "club_team_id": null,
      "position": "M",
      "rating": 5.95,
      "started": true,
      "played": true,
      "minutes_played": 90,
      "passing": {
        "total_passes": 37,
        "accurate_passes": 31,
        "key_passes": 0,
        "assists": 0,
        "total_crosses": 0,
        "accurate_crosses": 0,
        "total_long_balls": 4,
        "accurate_long_balls": 2
      },
      "shooting": {
        "goals": 0,
        "total_shots": 0,
        "shots_on_target": 0,
        "shots_off_target": 0,
        "blocked_shots": 0,
        "big_chances_created": 0,
        "expected_goals": 0,
        "expected_assists": 0,
        "np_expected_goals": null
      },
      "duels": {
        "duel_won": 2,
        "duel_lost": 3,
        "aerial_won": 0,
        "challenge_lost": 2,
        "won_contest": 0,
        "dispossessed": 0
      },
      "defending": {
        "tackles": 2,
        "interceptions": 1,
        "clearances": 1
      },
      "goalkeeping": {
        "saves": 0
      },
      "general": {
        "touches": 43,
        "fouls": 1,
        "was_fouled": 0,
        "offsides": 0,
        "yellow_cards": 0,
        "red_cards": 0,
        "possession_lost": 6,
        "player_subbed_on": null,
        "player_subbed_off": null
      }
    },
    {
      "player_id": "pl_6236640",
      "player_name": "Christopher Forrester",
      "team_id": "tm_79322",
      "club_team_id": null,
      "position": "M",
      "rating": 6.43,
      "started": true,
      "played": true,
      "minutes_played": 82,
      "passing": {
        "total_passes": 40,
        "accurate_passes": 38,
        "key_passes": 0,
        "assists": 0,
        "total_crosses": 0,
        "accurate_crosses": 0,
        "total_long_balls": 7,
        "accurate_long_balls": 6
      },
      "shooting": {
        "goals": 0,
        "total_shots": 1,
        "shots_on_target": 1,
        "shots_off_target": 0,
        "blocked_shots": 0,
        "big_chances_created": 0,
        "expected_goals": 0,
        "expected_assists": 0,
        "np_expected_goals": null
      },
      "duels": {
        "duel_won": 3,
        "duel_lost": 3,
        "aerial_won": 0,
        "challenge_lost": 1,
        "won_contest": 1,
        "dispossessed": 1
      },
      "defending": {
        "tackles": 2,
        "interceptions": 1,
        "clearances": 1
      },
      "goalkeeping": {
        "saves": 0
      },
      "general": {
        "touches": 52,
        "fouls": 1,
        "was_fouled": 0,
        "offsides": 0,
        "yellow_cards": 0,
        "red_cards": 0,
        "possession_lost": 4,
        "player_subbed_on": "pl_30410272",
        "player_subbed_off": null
      }
    },
    {
      "player_id": "pl_72970494",
      "player_name": "Jake Mulraney",
      "team_id": "tm_79322",
      "club_team_id": "tm_38765",
      "position": "F",
      "rating": 6.29,
      "started": true,
      "played": true,
      "minutes_played": 45,
      "passing": {
        "total_passes": 9,
        "accurate_passes": 8,
        "key_passes": 0,
        "assists": 0,
        "total_crosses": 2,
        "accurate_crosses": 0,
        "total_long_balls": 0,
        "accurate_long_balls": 0
      },
      "shooting": {
        "goals": 0,
        "total_shots": 0,
        "shots_on_target": 0,
        "shots_off_target": 0,
        "blocked_shots": 0,
        "big_chances_created": 0,
        "expected_goals": 0,
        "expected_assists": 0,
        "np_expected_goals": null
      },
      "duels": {
        "duel_won": 3,
        "duel_lost": 2,
        "aerial_won": 0,
        "challenge_lost": 0,
        "won_contest": 0,
        "dispossessed": 0
      },
      "defending": {
        "tackles": 1,
        "interceptions": 0,
        "clearances": 0
      },
      "goalkeeping": {
        "saves": 0
      },
      "general": {
        "touches": 17,
        "fouls": 2,
        "was_fouled": 2,
        "offsides": 0,
        "yellow_cards": 1,
        "red_cards": 0,
        "possession_lost": 4,
        "player_subbed_on": "pl_61056145",
        "player_subbed_off": null
      }
    },
    {
      "player_id": "pl_13851481",
      "player_name": "Joseph Anang",
      "team_id": "tm_79322",
      "club_team_id": null,
      "position": "G",
      "rating": 6.09,
      "started": true,
      "played": true,
      "minutes_played": 90,
      "passing": {
        "total_passes": 25,
        "accurate_passes": 18,
        "key_passes": 0,
        "assists": 0,
        "total_crosses": 0,
        "accurate_crosses": 0,
        "total_long_balls": 14,
        "accurate_long_balls": 7
      },
      "shooting": {
        "goals": 0,
        "total_shots": 0,
        "shots_on_target": 0,
        "shots_off_target": 0,
        "blocked_shots": 0,
        "big_chances_created": 0,
        "expected_goals": 0,
        "expected_assists": 0,
        "np_expected_goals": null
      },
      "duels": {
        "duel_won": 1,
        "duel_lost": 0,
        "aerial_won": 0,
        "challenge_lost": 0,
        "won_contest": 0,
        "dispossessed": 0
      },
      "defending": {
        "tackles": 1,
        "interceptions": 0,
        "clearances": 0
      },
      "goalkeeping": {
        "saves": 4
      },
      "general": {
        "touches": 35,
        "fouls": 0,
        "was_fouled": 0,
        "offsides": 0,
        "yellow_cards": 0,
        "red_cards": 0,
        "possession_lost": 7,
        "player_subbed_on": null,
        "player_subbed_off": null
      }
    },
    {
      "player_id": "pl_57996525",
      "player_name": "Joe Redmond",
      "team_id": "tm_79322",
      "club_team_id": null,
      "position": "D",
      "rating": 6.09,
      "started": true,
      "played": true,
      "minutes_played": 90,
      "passing": {
        "total_passes": 48,
        "accurate_passes": 45,
        "key_passes": 0,
        "assists": 0,
        "total_crosses": 0,
        "accurate_crosses": 0,
        "total_long_balls": 5,
        "accurate_long_balls": 3
      },
      "shooting": {
        "goals": 0,
        "total_shots": 0,
        "shots_on_target": 0,
        "shots_off_target": 0,
        "blocked_shots": 0,
        "big_chances_created": 0,
        "expected_goals": 0,
        "expected_assists": 0,
        "np_expected_goals": null
      },
      "duels": {
        "duel_won": 4,
        "duel_lost": 2,
        "aerial_won": 1,
        "challenge_lost": 0,
        "won_contest": 0,
        "dispossessed": 0
      },
      "defending": {
        "tackles": 2,
        "interceptions": 1,
        "clearances": 5
      },
      "goalkeeping": {
        "saves": 0
      },
      "general": {
        "touches": 62,
        "fouls": 1,
        "was_fouled": 1,
        "offsides": 0,
        "yellow_cards": 0,
        "red_cards": 0,
        "possession_lost": 4,
        "player_subbed_on": null,
        "player_subbed_off": null
      }
    },
    {
      "player_id": "pl_1368879",
      "player_name": "Ryan McLaughlin",
      "team_id": "tm_79322",
      "club_team_id": "tm_40588887",
      "position": "D",
      "rating": 6.27,
      "started": true,
      "played": true,
      "minutes_played": 90,
      "passing": {
        "total_passes": 30,
        "accurate_passes": 27,
        "key_passes": 0,
        "assists": 0,
        "total_crosses": 2,
        "accurate_crosses": 1,
        "total_long_balls": 2,
        "accurate_long_balls": 1
      },
      "shooting": {
        "goals": 0,
        "total_shots": 0,
        "shots_on_target": 0,
        "shots_off_target": 0,
        "blocked_shots": 0,
        "big_chances_created": 0,
        "expected_goals": 0,
        "expected_assists": 0,
        "np_expected_goals": null
      },
      "duels": {
        "duel_won": 2,
        "duel_lost": 2,
        "aerial_won": 0,
        "challenge_lost": 0,
        "won_contest": 0,
        "dispossessed": 1
      },
      "defending": {
        "tackles": 0,
        "interceptions": 1,
        "clearances": 0
      },
      "goalkeeping": {
        "saves": 0
      },
      "general": {
        "touches": 42,
        "fouls": 0,
        "was_fouled": 2,
        "offsides": 0,
        "yellow_cards": 0,
        "red_cards": 0,
        "possession_lost": 5,
        "player_subbed_on": null,
        "player_subbed_off": null
      }
    },
    {
      "player_id": "pl_97003399",
      "player_name": "Kian Leavy",
      "team_id": "tm_79322",
      "club_team_id": null,
      "position": "M",
      "rating": 6.09,
      "started": true,
      "played": true,
      "minutes_played": 82,
      "passing": {
        "total_passes": 20,
        "accurate_passes": 18,
        "key_passes": 0,
        "assists": 0,
        "total_crosses": 1,
        "accurate_crosses": 0,
        "total_long_balls": 1,
        "accurate_long_balls": 1
      },
      "shooting": {
        "goals": 0,
        "total_shots": 0,
        "shots_on_target": 0,
        "shots_off_target": 0,
        "blocked_shots": 0,
        "big_chances_created": 0,
        "expected_goals": 0,
        "expected_assists": 0,
        "np_expected_goals": null
      },
      "duels": {
        "duel_won": 3,
        "duel_lost": 4,
        "aerial_won": 0,
        "challenge_lost": 1,
        "won_contest": 2,
        "dispossessed": 1
      },
      "defending": {
        "tackles": 1,
        "interceptions": 1,
        "clearances": 1
      },
      "goalkeeping": {
        "saves": 0
      },
      "general": {
        "touches": 34,
        "fouls": 0,
        "was_fouled": 0,
        "offsides": 0,
        "yellow_cards": 0,
        "red_cards": 0,
        "possession_lost": 11,
        "player_subbed_on": "pl_84707556",
        "player_subbed_off": null
      }
    },
    {
      "player_id": "pl_30166567",
      "player_name": "Jason McClelland",
      "team_id": "tm_79322",
      "club_team_id": null,
      "position": "D",
      "rating": 5.6,
      "started": true,
      "played": true,
      "minutes_played": 90,
      "passing": {
        "total_passes": 29,
        "accurate_passes": 24,
        "key_passes": 2,
        "assists": 1,
        "total_crosses": 5,
        "accurate_crosses": 0,
        "total_long_balls": 6,
        "accurate_long_balls": 2
      },
      "shooting": {
        "goals": 0,
        "total_shots": 0,
        "shots_on_target": 0,
        "shots_off_target": 0,
        "blocked_shots": 0,
        "big_chances_created": 0,
        "expected_goals": 0,
        "expected_assists": 0,
        "np_expected_goals": null
      },
      "duels": {
        "duel_won": 3,
        "duel_lost": 6,
        "aerial_won": 0,
        "challenge_lost": 3,
        "won_contest": 1,
        "dispossessed": 1
      },
      "defending": {
        "tackles": 1,
        "interceptions": 1,
        "clearances": 2
      },
      "goalkeeping": {
        "saves": 0
      },
      "general": {
        "touches": 52,
        "fouls": 0,
        "was_fouled": 1,
        "offsides": 0,
        "yellow_cards": 0,
        "red_cards": 0,
        "possession_lost": 13,
        "player_subbed_on": null,
        "player_subbed_off": null
      }
    },
    {
      "player_id": "pl_25832022",
      "player_name": "Mason Melia",
      "team_id": "tm_79322",
      "club_team_id": "tm_4502201",
      "position": "F",
      "rating": 7.1,
      "started": true,
      "played": true,
      "minutes_played": 88,
      "passing": {
        "total_passes": 10,
        "accurate_passes": 9,
        "key_passes": 1,
        "assists": 0,
        "total_crosses": 0,
        "accurate_crosses": 0,
        "total_long_balls": 0,
        "accurate_long_balls": 0
      },
      "shooting": {
        "goals": 0,
        "total_shots": 1,
        "shots_on_target": 1,
        "shots_off_target": 0,
        "blocked_shots": 0,
        "big_chances_created": 0,
        "expected_goals": 0,
        "expected_assists": 0,
        "np_expected_goals": null
      },
      "duels": {
        "duel_won": 6,
        "duel_lost": 9,
        "aerial_won": 2,
        "challenge_lost": 1,
        "won_contest": 0,
        "dispossessed": 5
      },
      "defending": {
        "tackles": 1,
        "interceptions": 0,
        "clearances": 0
      },
      "goalkeeping": {
        "saves": 0
      },
      "general": {
        "touches": 25,
        "fouls": 0,
        "was_fouled": 3,
        "offsides": 0,
        "yellow_cards": 0,
        "red_cards": 0,
        "possession_lost": 9,
        "player_subbed_on": "pl_61501820",
        "player_subbed_off": null
      }
    },
    {
      "player_id": "pl_08357030",
      "player_name": "Simon Power",
      "team_id": "tm_79322",
      "club_team_id": null,
      "position": "F",
      "rating": 7.83,
      "started": true,
      "played": true,
      "minutes_played": 90,
      "passing": {
        "total_passes": 16,
        "accurate_passes": 14,
        "key_passes": 0,
        "assists": 0,
        "total_crosses": 5,
        "accurate_crosses": 0,
        "total_long_balls": 0,
        "accurate_long_balls": 0
      },
      "shooting": {
        "goals": 1,
        "total_shots": 2,
        "shots_on_target": 1,
        "shots_off_target": 1,
        "blocked_shots": 0,
        "big_chances_created": 0,
        "expected_goals": 0,
        "expected_assists": 0,
        "np_expected_goals": null
      },
      "duels": {
        "duel_won": 7,
        "duel_lost": 5,
        "aerial_won": 2,
        "challenge_lost": 0,
        "won_contest": 1,
        "dispossessed": 3
      },
      "defending": {
        "tackles": 2,
        "interceptions": 0,
        "clearances": 0
      },
      "goalkeeping": {
        "saves": 0
      },
      "general": {
        "touches": 42,
        "fouls": 0,
        "was_fouled": 2,
        "offsides": 0,
        "yellow_cards": 0,
        "red_cards": 0,
        "possession_lost": 14,
        "player_subbed_on": null,
        "player_subbed_off": null
      }
    },
    {
      "player_id": "pl_72536535",
      "player_name": "Tayyip Talha Sanuç",
      "team_id": "tm_10361",
      "club_team_id": null,
      "position": "D",
      "rating": 0,
      "started": false,
      "played": true,
      "minutes_played": 1,
      "passing": {
        "total_passes": 3,
        "accurate_passes": 3,
        "key_passes": 0,
        "assists": 0,
        "total_crosses": 0,
        "accurate_crosses": 0,
        "total_long_balls": 0,
        "accurate_long_balls": 0
      },
      "shooting": {
        "goals": 0,
        "total_shots": 0,
        "shots_on_target": 0,
        "shots_off_target": 0,
        "blocked_shots": 0,
        "big_chances_created": 0,
        "expected_goals": 0,
        "expected_assists": 0,
        "np_expected_goals": null
      },
      "duels": {
        "duel_won": 0,
        "duel_lost": 0,
        "aerial_won": 0,
        "challenge_lost": 0,
        "won_contest": 0,
        "dispossessed": 0
      },
      "defending": {
        "tackles": 0,
        "interceptions": 0,
        "clearances": 0
      },
      "goalkeeping": {
        "saves": 0
      },
      "general": {
        "touches": 3,
        "fouls": 0,
        "was_fouled": 0,
        "offsides": 0,
        "yellow_cards": 0,
        "red_cards": 0,
        "possession_lost": 0,
        "player_subbed_on": null,
        "player_subbed_off": "pl_29263116"
      }
    },
    {
      "player_id": "pl_29100926",
      "player_name": "Kartal Kayra Yılmaz",
      "team_id": "tm_10361",
      "club_team_id": null,
      "position": "M",
      "rating": 7.1,
      "started": false,
      "played": true,
      "minutes_played": 15,
      "passing": {
        "total_passes": 23,
        "accurate_passes": 23,
        "key_passes": 2,
        "assists": 0,
        "total_crosses": 1,
        "accurate_crosses": 0,
        "total_long_balls": 3,
        "accurate_long_balls": 3
      },
      "shooting": {
        "goals": 0,
        "total_shots": 1,
        "shots_on_target": 0,
        "shots_off_target": 1,
        "blocked_shots": 0,
        "big_chances_created": 0,
        "expected_goals": 0,
        "expected_assists": 0,
        "np_expected_goals": null
      },
      "duels": {
        "duel_won": 1,
        "duel_lost": 0,
        "aerial_won": 0,
        "challenge_lost": 0,
        "won_contest": 0,
        "dispossessed": 0
      },
      "defending": {
        "tackles": 1,
        "interceptions": 0,
        "clearances": 0
      },
      "goalkeeping": {
        "saves": 0
      },
      "general": {
        "touches": 27,
        "fouls": 0,
        "was_fouled": 0,
        "offsides": 0,
        "yellow_cards": 0,
        "red_cards": 0,
        "possession_lost": 1,
        "player_subbed_on": null,
        "player_subbed_off": "pl_58717116"
      }
    },
    {
      "player_id": "pl_3875532",
      "player_name": "Tayfur Bingöl",
      "team_id": "tm_10361",
      "club_team_id": "tm_47528",
      "position": "M",
      "rating": 6.43,
      "started": false,
      "played": true,
      "minutes_played": 45,
      "passing": {
        "total_passes": 46,
        "accurate_passes": 44,
        "key_passes": 1,
        "assists": 0,
        "total_crosses": 0,
        "accurate_crosses": 0,
        "total_long_balls": 1,
        "accurate_long_balls": 1
      },
      "shooting": {
        "goals": 0,
        "total_shots": 0,
        "shots_on_target": 0,
        "shots_off_target": 0,
        "blocked_shots": 0,
        "big_chances_created": 0,
        "expected_goals": 0,
        "expected_assists": 0,
        "np_expected_goals": null
      },
      "duels": {
        "duel_won": 2,
        "duel_lost": 1,
        "aerial_won": 0,
        "challenge_lost": 1,
        "won_contest": 0,
        "dispossessed": 0
      },
      "defending": {
        "tackles": 2,
        "interceptions": 2,
        "clearances": 1
      },
      "goalkeeping": {
        "saves": 0
      },
      "general": {
        "touches": 58,
        "fouls": 0,
        "was_fouled": 0,
        "offsides": 0,
        "yellow_cards": 0,
        "red_cards": 0,
        "possession_lost": 3,
        "player_subbed_on": null,
        "player_subbed_off": "pl_7257031"
      }
    },
    {
      "player_id": "pl_29665939",
      "player_name": "Amir Hadžiahmetović",
      "team_id": "tm_10361",
      "club_team_id": null,
      "position": "M",
      "rating": 0,
      "started": false,
      "played": true,
      "minutes_played": 1,
      "passing": {
        "total_passes": 5,
        "accurate_passes": 4,
        "key_passes": 0,
        "assists": 0,
        "total_crosses": 0,
        "accurate_crosses": 0,
        "total_long_balls": 1,
        "accurate_long_balls": 0
      },
      "shooting": {
        "goals": 0,
        "total_shots": 0,
        "shots_on_target": 0,
        "shots_off_target": 0,
        "blocked_shots": 0,
        "big_chances_created": 0,
        "expected_goals": 0,
        "expected_assists": 0,
        "np_expected_goals": null
      },
      "duels": {
        "duel_won": 1,
        "duel_lost": 0,
        "aerial_won": 0,
        "challenge_lost": 0,
        "won_contest": 0,
        "dispossessed": 0
      },
      "defending": {
        "tackles": 1,
        "interceptions": 0,
        "clearances": 0
      },
      "goalkeeping": {
        "saves": 0
      },
      "general": {
        "touches": 6,
        "fouls": 0,
        "was_fouled": 0,
        "offsides": 0,
        "yellow_cards": 0,
        "red_cards": 0,
        "possession_lost": 1,
        "player_subbed_on": null,
        "player_subbed_off": "pl_29805153"
      }
    },
    {
      "player_id": "pl_25132677",
      "player_name": "Keny Arroyo",
      "team_id": "tm_10361",
      "club_team_id": "tm_01988",
      "position": "M",
      "rating": 7.1,
      "started": false,
      "played": true,
      "minutes_played": 32,
      "passing": {
        "total_passes": 22,
        "accurate_passes": 19,
        "key_passes": 1,
        "assists": 0,
        "total_crosses": 0,
        "accurate_crosses": 0,
        "total_long_balls": 1,
        "accurate_long_balls": 0
      },
      "shooting": {
        "goals": 0,
        "total_shots": 3,
        "shots_on_target": 2,
        "shots_off_target": 0,
        "blocked_shots": 1,
        "big_chances_created": 0,
        "expected_goals": 0,
        "expected_assists": 0,
        "np_expected_goals": null
      },
      "duels": {
        "duel_won": 4,
        "duel_lost": 3,
        "aerial_won": 1,
        "challenge_lost": 0,
        "won_contest": 2,
        "dispossessed": 0
      },
      "defending": {
        "tackles": 1,
        "interceptions": 0,
        "clearances": 0
      },
      "goalkeeping": {
        "saves": 0
      },
      "general": {
        "touches": 31,
        "fouls": 2,
        "was_fouled": 0,
        "offsides": 0,
        "yellow_cards": 0,
        "red_cards": 0,
        "possession_lost": 6,
        "player_subbed_on": null,
        "player_subbed_off": "pl_13761573"
      }
    },
    {
      "player_id": "pl_83279934",
      "player_name": "Luke Turner",
      "team_id": "tm_79322",
      "club_team_id": null,
      "position": "D",
      "rating": 6.71,
      "started": false,
      "played": true,
      "minutes_played": 45,
      "passing": {
        "total_passes": 15,
        "accurate_passes": 12,
        "key_passes": 0,
        "assists": 0,
        "total_crosses": 1,
        "accurate_crosses": 1,
        "total_long_balls": 3,
        "accurate_long_balls": 1
      },
      "shooting": {
        "goals": 0,
        "total_shots": 0,
        "shots_on_target": 0,
        "shots_off_target": 0,
        "blocked_shots": 0,
        "big_chances_created": 0,
        "expected_goals": 0,
        "expected_assists": 0,
        "np_expected_goals": null
      },
      "duels": {
        "duel_won": 3,
        "duel_lost": 1,
        "aerial_won": 1,
        "challenge_lost": 0,
        "won_contest": 0,
        "dispossessed": 1
      },
      "defending": {
        "tackles": 1,
        "interceptions": 0,
        "clearances": 0
      },
      "goalkeeping": {
        "saves": 0
      },
      "general": {
        "touches": 23,
        "fouls": 0,
        "was_fouled": 1,
        "offsides": 0,
        "yellow_cards": 0,
        "red_cards": 0,
        "possession_lost": 5,
        "player_subbed_on": null,
        "player_subbed_off": "pl_30485343"
      }
    },
    {
      "player_id": "pl_61056145",
      "player_name": "Axel Sjoberg",
      "team_id": "tm_79322",
      "club_team_id": "tm_8425738",
      "position": "D",
      "rating": 7.36,
      "started": false,
      "played": true,
      "minutes_played": 45,
      "passing": {
        "total_passes": 14,
        "accurate_passes": 13,
        "key_passes": 1,
        "assists": 0,
        "total_crosses": 1,
        "accurate_crosses": 1,
        "total_long_balls": 0,
        "accurate_long_balls": 0
      },
      "shooting": {
        "goals": 0,
        "total_shots": 0,
        "shots_on_target": 0,
        "shots_off_target": 0,
        "blocked_shots": 0,
        "big_chances_created": 1,
        "expected_goals": 0,
        "expected_assists": 0,
        "np_expected_goals": null
      },
      "duels": {
        "duel_won": 1,
        "duel_lost": 0,
        "aerial_won": 0,
        "challenge_lost": 0,
        "won_contest": 0,
        "dispossessed": 0
      },
      "defending": {
        "tackles": 0,
        "interceptions": 0,
        "clearances": 1
      },
      "goalkeeping": {
        "saves": 0
      },
      "general": {
        "touches": 19,
        "fouls": 0,
        "was_fouled": 1,
        "offsides": 0,
        "yellow_cards": 0,
        "red_cards": 0,
        "possession_lost": 1,
        "player_subbed_on": null,
        "player_subbed_off": "pl_72970494"
      }
    },
    {
      "player_id": "pl_61501820",
      "player_name": "Brandon Kavanagh",
      "team_id": "tm_79322",
      "club_team_id": "tm_10595",
      "position": "M",
      "rating": 0,
      "started": false,
      "played": true,
      "minutes_played": 3,
      "passing": {
        "total_passes": 2,
        "accurate_passes": 1,
        "key_passes": 0,
        "assists": 0,
        "total_crosses": 0,
        "accurate_crosses": 0,
        "total_long_balls": 0,
        "accurate_long_balls": 0
      },
      "shooting": {
        "goals": 0,
        "total_shots": 0,
        "shots_on_target": 0,
        "shots_off_target": 0,
        "blocked_shots": 0,
        "big_chances_created": 0,
        "expected_goals": 0,
        "expected_assists": 0,
        "np_expected_goals": null
      },
      "duels": {
        "duel_won": 0,
        "duel_lost": 1,
        "aerial_won": 0,
        "challenge_lost": 0,
        "won_contest": 0,
        "dispossessed": 0
      },
      "defending": {
        "tackles": 0,
        "interceptions": 0,
        "clearances": 0
      },
      "goalkeeping": {
        "saves": 0
      },
      "general": {
        "touches": 3,
        "fouls": 0,
        "was_fouled": 0,
        "offsides": 0,
        "yellow_cards": 0,
        "red_cards": 0,
        "possession_lost": 2,
        "player_subbed_on": null,
        "player_subbed_off": "pl_25832022"
      }
    },
    {
      "player_id": "pl_30410272",
      "player_name": "Barry Baggley",
      "team_id": "tm_79322",
      "club_team_id": null,
      "position": "M",
      "rating": 6.29,
      "started": false,
      "played": true,
      "minutes_played": 9,
      "passing": {
        "total_passes": 7,
        "accurate_passes": 7,
        "key_passes": 0,
        "assists": 0,
        "total_crosses": 0,
        "accurate_crosses": 0,
        "total_long_balls": 1,
        "accurate_long_balls": 1
      },
      "shooting": {
        "goals": 0,
        "total_shots": 0,
        "shots_on_target": 0,
        "shots_off_target": 0,
        "blocked_shots": 0,
        "big_chances_created": 0,
        "expected_goals": 0,
        "expected_assists": 0,
        "np_expected_goals": null
      },
      "duels": {
        "duel_won": 0,
        "duel_lost": 1,
        "aerial_won": 0,
        "challenge_lost": 0,
        "won_contest": 0,
        "dispossessed": 1
      },
      "defending": {
        "tackles": 0,
        "interceptions": 0,
        "clearances": 0
      },
      "goalkeeping": {
        "saves": 0
      },
      "general": {
        "touches": 8,
        "fouls": 0,
        "was_fouled": 0,
        "offsides": 0,
        "yellow_cards": 0,
        "red_cards": 0,
        "possession_lost": 1,
        "player_subbed_on": null,
        "player_subbed_off": "pl_6236640"
      }
    },
    {
      "player_id": "pl_84707556",
      "player_name": "Conor Carty",
      "team_id": "tm_79322",
      "club_team_id": "tm_04220",
      "position": "F",
      "rating": 6.09,
      "started": false,
      "played": true,
      "minutes_played": 9,
      "passing": {
        "total_passes": 0,
        "accurate_passes": 0,
        "key_passes": 0,
        "assists": 0,
        "total_crosses": 0,
        "accurate_crosses": 0,
        "total_long_balls": 0,
        "accurate_long_balls": 0
      },
      "shooting": {
        "goals": 0,
        "total_shots": 0,
        "shots_on_target": 0,
        "shots_off_target": 0,
        "blocked_shots": 0,
        "big_chances_created": 0,
        "expected_goals": 0,
        "expected_assists": 0,
        "np_expected_goals": null
      },
      "duels": {
        "duel_won": 0,
        "duel_lost": 0,
        "aerial_won": 0,
        "challenge_lost": 0,
        "won_contest": 0,
        "dispossessed": 0
      },
      "defending": {
        "tackles": 0,
        "interceptions": 0,
        "clearances": 0
      },
      "goalkeeping": {
        "saves": 0
      },
      "general": {
        "touches": 0,
        "fouls": 0,
        "was_fouled": 0,
        "offsides": 0,
        "yellow_cards": 0,
        "red_cards": 0,
        "possession_lost": 0,
        "player_subbed_on": null,
        "player_subbed_off": "pl_97003399"
      }
    },
    {
      "player_id": "pl_61532254",
      "player_name": "Ersin Destanoğlu",
      "team_id": "tm_10361",
      "club_team_id": null,
      "position": "G",
      "rating": 0,
      "started": false,
      "played": false,
      "minutes_played": 0,
      "passing": {
        "total_passes": 0,
        "accurate_passes": 0,
        "key_passes": 0,
        "assists": 0,
        "total_crosses": 0,
        "accurate_crosses": 0,
        "total_long_balls": 0,
        "accurate_long_balls": 0
      },
      "shooting": {
        "goals": 0,
        "total_shots": 0,
        "shots_on_target": 0,
        "shots_off_target": 0,
        "blocked_shots": 0,
        "big_chances_created": 0,
        "expected_goals": 0,
        "expected_assists": 0,
        "np_expected_goals": null
      },
      "duels": {
        "duel_won": 0,
        "duel_lost": 0,
        "aerial_won": 0,
        "challenge_lost": 0,
        "won_contest": 0,
        "dispossessed": 0
      },
      "defending": {
        "tackles": 0,
        "interceptions": 0,
        "clearances": 0
      },
      "goalkeeping": {
        "saves": 0
      },
      "general": {
        "touches": 0,
        "fouls": 0,
        "was_fouled": 0,
        "offsides": 0,
        "yellow_cards": 0,
        "red_cards": 0,
        "possession_lost": 0,
        "player_subbed_on": null,
        "player_subbed_off": null
      }
    },
    {
      "player_id": "pl_13183918",
      "player_name": "Emre Bilgin",
      "team_id": "tm_10361",
      "club_team_id": null,
      "position": "G",
      "rating": 0,
      "started": false,
      "played": false,
      "minutes_played": 0,
      "passing": {
        "total_passes": 0,
        "accurate_passes": 0,
        "key_passes": 0,
        "assists": 0,
        "total_crosses": 0,
        "accurate_crosses": 0,
        "total_long_balls": 0,
        "accurate_long_balls": 0
      },
      "shooting": {
        "goals": 0,
        "total_shots": 0,
        "shots_on_target": 0,
        "shots_off_target": 0,
        "blocked_shots": 0,
        "big_chances_created": 0,
        "expected_goals": 0,
        "expected_assists": 0,
        "np_expected_goals": null
      },
      "duels": {
        "duel_won": 0,
        "duel_lost": 0,
        "aerial_won": 0,
        "challenge_lost": 0,
        "won_contest": 0,
        "dispossessed": 0
      },
      "defending": {
        "tackles": 0,
        "interceptions": 0,
        "clearances": 0
      },
      "goalkeeping": {
        "saves": 0
      },
      "general": {
        "touches": 0,
        "fouls": 0,
        "was_fouled": 0,
        "offsides": 0,
        "yellow_cards": 0,
        "red_cards": 0,
        "possession_lost": 0,
        "player_subbed_on": null,
        "player_subbed_off": null
      }
    },
    {
      "player_id": "pl_01828228",
      "player_name": "Serkan Emrecan Terzi",
      "team_id": "tm_10361",
      "club_team_id": null,
      "position": "D",
      "rating": 0,
      "started": false,
      "played": false,
      "minutes_played": 0,
      "passing": {
        "total_passes": 0,
        "accurate_passes": 0,
        "key_passes": 0,
        "assists": 0,
        "total_crosses": 0,
        "accurate_crosses": 0,
        "total_long_balls": 0,
        "accurate_long_balls": 0
      },
      "shooting": {
        "goals": 0,
        "total_shots": 0,
        "shots_on_target": 0,
        "shots_off_target": 0,
        "blocked_shots": 0,
        "big_chances_created": 0,
        "expected_goals": 0,
        "expected_assists": 0,
        "np_expected_goals": null
      },
      "duels": {
        "duel_won": 0,
        "duel_lost": 0,
        "aerial_won": 0,
        "challenge_lost": 0,
        "won_contest": 0,
        "dispossessed": 0
      },
      "defending": {
        "tackles": 0,
        "interceptions": 0,
        "clearances": 0
      },
      "goalkeeping": {
        "saves": 0
      },
      "general": {
        "touches": 0,
        "fouls": 0,
        "was_fouled": 0,
        "offsides": 0,
        "yellow_cards": 0,
        "red_cards": 0,
        "possession_lost": 0,
        "player_subbed_on": null,
        "player_subbed_off": null
      }
    },
    {
      "player_id": "pl_093493",
      "player_name": "Necip Uysal",
      "team_id": "tm_10361",
      "club_team_id": null,
      "position": "D",
      "rating": 0,
      "started": false,
      "played": false,
      "minutes_played": 0,
      "passing": {
        "total_passes": 0,
        "accurate_passes": 0,
        "key_passes": 0,
        "assists": 0,
        "total_crosses": 0,
        "accurate_crosses": 0,
        "total_long_balls": 0,
        "accurate_long_balls": 0
      },
      "shooting": {
        "goals": 0,
        "total_shots": 0,
        "shots_on_target": 0,
        "shots_off_target": 0,
        "blocked_shots": 0,
        "big_chances_created": 0,
        "expected_goals": 0,
        "expected_assists": 0,
        "np_expected_goals": null
      },
      "duels": {
        "duel_won": 0,
        "duel_lost": 0,
        "aerial_won": 0,
        "challenge_lost": 0,
        "won_contest": 0,
        "dispossessed": 0
      },
      "defending": {
        "tackles": 0,
        "interceptions": 0,
        "clearances": 0
      },
      "goalkeeping": {
        "saves": 0
      },
      "general": {
        "touches": 0,
        "fouls": 0,
        "was_fouled": 0,
        "offsides": 0,
        "yellow_cards": 0,
        "red_cards": 0,
        "possession_lost": 0,
        "player_subbed_on": null,
        "player_subbed_off": null
      }
    },
    {
      "player_id": "pl_4001500",
      "player_name": "Salih Uçan",
      "team_id": "tm_10361",
      "club_team_id": null,
      "position": "M",
      "rating": 0,
      "started": false,
      "played": false,
      "minutes_played": 0,
      "passing": {
        "total_passes": 0,
        "accurate_passes": 0,
        "key_passes": 0,
        "assists": 0,
        "total_crosses": 0,
        "accurate_crosses": 0,
        "total_long_balls": 0,
        "accurate_long_balls": 0
      },
      "shooting": {
        "goals": 0,
        "total_shots": 0,
        "shots_on_target": 0,
        "shots_off_target": 0,
        "blocked_shots": 0,
        "big_chances_created": 0,
        "expected_goals": 0,
        "expected_assists": 0,
        "np_expected_goals": null
      },
      "duels": {
        "duel_won": 0,
        "duel_lost": 0,
        "aerial_won": 0,
        "challenge_lost": 0,
        "won_contest": 0,
        "dispossessed": 0
      },
      "defending": {
        "tackles": 0,
        "interceptions": 0,
        "clearances": 0
      },
      "goalkeeping": {
        "saves": 0
      },
      "general": {
        "touches": 0,
        "fouls": 0,
        "was_fouled": 0,
        "offsides": 0,
        "yellow_cards": 0,
        "red_cards": 0,
        "possession_lost": 0,
        "player_subbed_on": null,
        "player_subbed_off": null
      }
    },
    {
      "player_id": "pl_84069878",
      "player_name": "Mutassim Al-Musrati",
      "team_id": "tm_10361",
      "club_team_id": null,
      "position": "M",
      "rating": 0,
      "started": false,
      "played": false,
      "minutes_played": 0,
      "passing": {
        "total_passes": 0,
        "accurate_passes": 0,
        "key_passes": 0,
        "assists": 0,
        "total_crosses": 0,
        "accurate_crosses": 0,
        "total_long_balls": 0,
        "accurate_long_balls": 0
      },
      "shooting": {
        "goals": 0,
        "total_shots": 0,
        "shots_on_target": 0,
        "shots_off_target": 0,
        "blocked_shots": 0,
        "big_chances_created": 0,
        "expected_goals": 0,
        "expected_assists": 0,
        "np_expected_goals": null
      },
      "duels": {
        "duel_won": 0,
        "duel_lost": 0,
        "aerial_won": 0,
        "challenge_lost": 0,
        "won_contest": 0,
        "dispossessed": 0
      },
      "defending": {
        "tackles": 0,
        "interceptions": 0,
        "clearances": 0
      },
      "goalkeeping": {
        "saves": 0
      },
      "general": {
        "touches": 0,
        "fouls": 0,
        "was_fouled": 0,
        "offsides": 0,
        "yellow_cards": 0,
        "red_cards": 0,
        "possession_lost": 0,
        "player_subbed_on": null,
        "player_subbed_off": null
      }
    },
    {
      "player_id": "pl_62145301",
      "player_name": "Sean Molloy",
      "team_id": "tm_79322",
      "club_team_id": null,
      "position": "G",
      "rating": 0,
      "started": false,
      "played": false,
      "minutes_played": 0,
      "passing": {
        "total_passes": 0,
        "accurate_passes": 0,
        "key_passes": 0,
        "assists": 0,
        "total_crosses": 0,
        "accurate_crosses": 0,
        "total_long_balls": 0,
        "accurate_long_balls": 0
      },
      "shooting": {
        "goals": 0,
        "total_shots": 0,
        "shots_on_target": 0,
        "shots_off_target": 0,
        "blocked_shots": 0,
        "big_chances_created": 0,
        "expected_goals": 0,
        "expected_assists": 0,
        "np_expected_goals": null
      },
      "duels": {
        "duel_won": 0,
        "duel_lost": 0,
        "aerial_won": 0,
        "challenge_lost": 0,
        "won_contest": 0,
        "dispossessed": 0
      },
      "defending": {
        "tackles": 0,
        "interceptions": 0,
        "clearances": 0
      },
      "goalkeeping": {
        "saves": 0
      },
      "general": {
        "touches": 0,
        "fouls": 0,
        "was_fouled": 0,
        "offsides": 0,
        "yellow_cards": 0,
        "red_cards": 0,
        "possession_lost": 0,
        "player_subbed_on": null,
        "player_subbed_off": null
      }
    },
    {
      "player_id": "pl_0208049",
      "player_name": "Danny Rogers",
      "team_id": "tm_79322",
      "club_team_id": null,
      "position": "G",
      "rating": 0,
      "started": false,
      "played": false,
      "minutes_played": 0,
      "passing": {
        "total_passes": 0,
        "accurate_passes": 0,
        "key_passes": 0,
        "assists": 0,
        "total_crosses": 0,
        "accurate_crosses": 0,
        "total_long_balls": 0,
        "accurate_long_balls": 0
      },
      "shooting": {
        "goals": 0,
        "total_shots": 0,
        "shots_on_target": 0,
        "shots_off_target": 0,
        "blocked_shots": 0,
        "big_chances_created": 0,
        "expected_goals": 0,
        "expected_assists": 0,
        "np_expected_goals": null
      },
      "duels": {
        "duel_won": 0,
        "duel_lost": 0,
        "aerial_won": 0,
        "challenge_lost": 0,
        "won_contest": 0,
        "dispossessed": 0
      },
      "defending": {
        "tackles": 0,
        "interceptions": 0,
        "clearances": 0
      },
      "goalkeeping": {
        "saves": 0
      },
      "general": {
        "touches": 0,
        "fouls": 0,
        "was_fouled": 0,
        "offsides": 0,
        "yellow_cards": 0,
        "red_cards": 0,
        "possession_lost": 0,
        "player_subbed_on": null,
        "player_subbed_off": null
      }
    },
    {
      "player_id": "pl_30355427",
      "player_name": "Al-Amin Kazeem",
      "team_id": "tm_79322",
      "club_team_id": "tm_9779104",
      "position": "D",
      "rating": 0,
      "started": false,
      "played": false,
      "minutes_played": 0,
      "passing": {
        "total_passes": 0,
        "accurate_passes": 0,
        "key_passes": 0,
        "assists": 0,
        "total_crosses": 0,
        "accurate_crosses": 0,
        "total_long_balls": 0,
        "accurate_long_balls": 0
      },
      "shooting": {
        "goals": 0,
        "total_shots": 0,
        "shots_on_target": 0,
        "shots_off_target": 0,
        "blocked_shots": 0,
        "big_chances_created": 0,
        "expected_goals": 0,
        "expected_assists": 0,
        "np_expected_goals": null
      },
      "duels": {
        "duel_won": 0,
        "duel_lost": 0,
        "aerial_won": 0,
        "challenge_lost": 0,
        "won_contest": 0,
        "dispossessed": 0
      },
      "defending": {
        "tackles": 0,
        "interceptions": 0,
        "clearances": 0
      },
      "goalkeeping": {
        "saves": 0
      },
      "general": {
        "touches": 0,
        "fouls": 0,
        "was_fouled": 0,
        "offsides": 0,
        "yellow_cards": 0,
        "red_cards": 0,
        "possession_lost": 0,
        "player_subbed_on": null,
        "player_subbed_off": null
      }
    },
    {
      "player_id": "pl_61592050",
      "player_name": "Jordon Garrick",
      "team_id": "tm_79322",
      "club_team_id": "tm_334405",
      "position": "M",
      "rating": 0,
      "started": false,
      "played": false,
      "minutes_played": 0,
      "passing": {
        "total_passes": 0,
        "accurate_passes": 0,
        "key_passes": 0,
        "assists": 0,
        "total_crosses": 0,
        "accurate_crosses": 0,
        "total_long_balls": 0,
        "accurate_long_balls": 0
      },
      "shooting": {
        "goals": 0,
        "total_shots": 0,
        "shots_on_target": 0,
        "shots_off_target": 0,
        "blocked_shots": 0,
        "big_chances_created": 0,
        "expected_goals": 0,
        "expected_assists": 0,
        "np_expected_goals": null
      },
      "duels": {
        "duel_won": 0,
        "duel_lost": 0,
        "aerial_won": 0,
        "challenge_lost": 0,
        "won_contest": 0,
        "dispossessed": 0
      },
      "defending": {
        "tackles": 0,
        "interceptions": 0,
        "clearances": 0
      },
      "goalkeeping": {
        "saves": 0
      },
      "general": {
        "touches": 0,
        "fouls": 0,
        "was_fouled": 0,
        "offsides": 0,
        "yellow_cards": 0,
        "red_cards": 0,
        "possession_lost": 0,
        "player_subbed_on": null,
        "player_subbed_off": null
      }
    },
    {
      "player_id": "pl_19331639",
      "player_name": "Darren Robinson",
      "team_id": "tm_79322",
      "club_team_id": "tm_0872",
      "position": "M",
      "rating": 0,
      "started": false,
      "played": false,
      "minutes_played": 0,
      "passing": {
        "total_passes": 0,
        "accurate_passes": 0,
        "key_passes": 0,
        "assists": 0,
        "total_crosses": 0,
        "accurate_crosses": 0,
        "total_long_balls": 0,
        "accurate_long_balls": 0
      },
      "shooting": {
        "goals": 0,
        "total_shots": 0,
        "shots_on_target": 0,
        "shots_off_target": 0,
        "blocked_shots": 0,
        "big_chances_created": 0,
        "expected_goals": 0,
        "expected_assists": 0,
        "np_expected_goals": null
      },
      "duels": {
        "duel_won": 0,
        "duel_lost": 0,
        "aerial_won": 0,
        "challenge_lost": 0,
        "won_contest": 0,
        "dispossessed": 0
      },
      "defending": {
        "tackles": 0,
        "interceptions": 0,
        "clearances": 0
      },
      "goalkeeping": {
        "saves": 0
      },
      "general": {
        "touches": 0,
        "fouls": 0,
        "was_fouled": 0,
        "offsides": 0,
        "yellow_cards": 0,
        "red_cards": 0,
        "possession_lost": 0,
        "player_subbed_on": null,
        "player_subbed_off": null
      }
    },
    {
      "player_id": "pl_26967359",
      "player_name": "Kian Quigley",
      "team_id": "tm_79322",
      "club_team_id": null,
      "position": "M",
      "rating": 0,
      "started": false,
      "played": false,
      "minutes_played": 0,
      "passing": {
        "total_passes": 0,
        "accurate_passes": 0,
        "key_passes": 0,
        "assists": 0,
        "total_crosses": 0,
        "accurate_crosses": 0,
        "total_long_balls": 0,
        "accurate_long_balls": 0
      },
      "shooting": {
        "goals": 0,
        "total_shots": 0,
        "shots_on_target": 0,
        "shots_off_target": 0,
        "blocked_shots": 0,
        "big_chances_created": 0,
        "expected_goals": 0,
        "expected_assists": 0,
        "np_expected_goals": null
      },
      "duels": {
        "duel_won": 0,
        "duel_lost": 0,
        "aerial_won": 0,
        "challenge_lost": 0,
        "won_contest": 0,
        "dispossessed": 0
      },
      "defending": {
        "tackles": 0,
        "interceptions": 0,
        "clearances": 0
      },
      "goalkeeping": {
        "saves": 0
      },
      "general": {
        "touches": 0,
        "fouls": 0,
        "was_fouled": 0,
        "offsides": 0,
        "yellow_cards": 0,
        "red_cards": 0,
        "possession_lost": 0,
        "player_subbed_on": null,
        "player_subbed_off": null
      }
    },
    {
      "player_id": "pl_46174581",
      "player_name": "Billy Hayes",
      "team_id": "tm_79322",
      "club_team_id": null,
      "position": "F",
      "rating": 0,
      "started": false,
      "played": false,
      "minutes_played": 0,
      "passing": {
        "total_passes": 0,
        "accurate_passes": 0,
        "key_passes": 0,
        "assists": 0,
        "total_crosses": 0,
        "accurate_crosses": 0,
        "total_long_balls": 0,
        "accurate_long_balls": 0
      },
      "shooting": {
        "goals": 0,
        "total_shots": 0,
        "shots_on_target": 0,
        "shots_off_target": 0,
        "blocked_shots": 0,
        "big_chances_created": 0,
        "expected_goals": 0,
        "expected_assists": 0,
        "np_expected_goals": null
      },
      "duels": {
        "duel_won": 0,
        "duel_lost": 0,
        "aerial_won": 0,
        "challenge_lost": 0,
        "won_contest": 0,
        "dispossessed": 0
      },
      "defending": {
        "tackles": 0,
        "interceptions": 0,
        "clearances": 0
      },
      "goalkeeping": {
        "saves": 0
      },
      "general": {
        "touches": 0,
        "fouls": 0,
        "was_fouled": 0,
        "offsides": 0,
        "yellow_cards": 0,
        "red_cards": 0,
        "possession_lost": 0,
        "player_subbed_on": null,
        "player_subbed_off": null
      }
    }
  ]
}